<?xml version="1.0" encoding="utf-8"?><toc><breadcrumbs><li><a href="R_Project_32feet_NET.htm">32feet</a></li><li><a href="R_Project_32feet_NET.htm">Namespaces</a></li><li><a href="N_InTheHand_Net_Bluetooth.htm">In<wbr />The<wbr />Hand.<wbr />Net.<wbr />Bluetooth</a></li></breadcrumbs><tocItems><li><a id="T_InTheHand_Net_Bluetooth_BluetoothDevicePicker" class="has-submenu" href="T_InTheHand_Net_Bluetooth_BluetoothDevicePicker.htm"><span data-tocFile="../toc/IDACA.xml" class="icon toggle" onclick="ToggleExpandCollapse(this); return false;"><i class="fa fa-angle-right"> </i></span>Bluetooth<wbr />Device<wbr />Picker</a><ul class="toc-menu is-hidden"> </ul></li><li><a id="T_InTheHand_Net_Bluetooth_BluetoothProtocol" class="has-submenu" href="T_InTheHand_Net_Bluetooth_BluetoothProtocol.htm"><span data-tocFile="../toc/IDBCA.xml" class="icon toggle" onclick="ToggleExpandCollapse(this); return false;"><i class="fa fa-angle-right"> </i></span>Bluetooth<wbr />Protocol</a><ul class="toc-menu is-hidden"> </ul></li><li><a id="T_InTheHand_Net_Bluetooth_BluetoothRadio" class="has-submenu" href="T_InTheHand_Net_Bluetooth_BluetoothRadio.htm"><span data-tocFile="../toc/IDCCA.xml" class="icon toggle" onclick="ToggleExpandCollapse(this); return false;"><i class="fa fa-angle-right"> </i></span>Bluetooth<wbr />Radio</a><ul class="toc-menu is-hidden"> </ul></li><li><a id="T_InTheHand_Net_Bluetooth_BluetoothSecurity" class="has-submenu" href="T_InTheHand_Net_Bluetooth_BluetoothSecurity.htm"><span data-tocFile="../toc/IDDCA.xml" class="icon toggle" onclick="ToggleExpandCollapse(this); return false;"><i class="fa fa-angle-right"> </i></span>Bluetooth<wbr />Security</a><ul class="toc-menu is-hidden"> </ul></li><li><a id="T_InTheHand_Net_Bluetooth_BluetoothService" class="has-submenu" href="T_InTheHand_Net_Bluetooth_BluetoothService.htm"><span data-tocFile="../toc/IDECA.xml" class="icon toggle" onclick="ToggleExpandCollapse(this); return false;"><i class="fa fa-angle-right"> </i></span>Bluetooth<wbr />Service</a><ul class="toc-menu is-hidden"> </ul></li><li><a id="T_InTheHand_Net_Bluetooth_BluetoothVersion" href="T_InTheHand_Net_Bluetooth_BluetoothVersion.htm">Bluetooth<wbr />Version</a></li><li><a id="T_InTheHand_Net_Bluetooth_ClassOfDevice" class="has-submenu" href="T_InTheHand_Net_Bluetooth_ClassOfDevice.htm"><span data-tocFile="../toc/IDGCA.xml" class="icon toggle" onclick="ToggleExpandCollapse(this); return false;"><i class="fa fa-angle-right"> </i></span>Class<wbr />Of<wbr />Device</a><ul class="toc-menu is-hidden"> </ul></li><li><a id="T_InTheHand_Net_Bluetooth_DeviceClass" href="T_InTheHand_Net_Bluetooth_DeviceClass.htm">Device<wbr />Class</a></li><li><a id="T_InTheHand_Net_Bluetooth_RadioMode" href="T_InTheHand_Net_Bluetooth_RadioMode.htm">Radio<wbr />Mode</a></li><li><a id="T_InTheHand_Net_Bluetooth_ServiceClass" href="T_InTheHand_Net_Bluetooth_ServiceClass.htm">Service<wbr />Class</a></li></tocItems></toc>